sidSimpleNN/__init__.py
sidSimpleNN/autoencoder.py
sidSimpleNN/function.py
sidSimpleNN/mainTrain.py
sidSimpleNN/myNN.py
sidSimpleNN-0.2.8.dist-info/LICENSE.txt
sidSimpleNN-0.2.8.dist-info/METADATA
sidSimpleNN-0.2.8.dist-info/WHEEL
sidSimpleNN-0.2.8.dist-info/top_level.txt
sidSimpleNN-0.2.8.dist-info/RECORD
