Metadata-Version: 2.1
Name: sidSimpleNN
Version: 0.2.8
Summary: Multilayered Perceptron NN light weight, make, train, test models
Home-page: UNKNOWN
Author: sid007
Author-email: sid700710@gmail.com
License: MIT
Download-URL: https://pypi.org/project/sidSimpleNN/
Keywords: sidSimpleNN
Platform: UNKNOWN
